typecheck/__init__.py
typecheck/checker.py
typeguarder-0.1.dist-info/LICENSE
typeguarder-0.1.dist-info/METADATA
typeguarder-0.1.dist-info/WHEEL
typeguarder-0.1.dist-info/top_level.txt
typeguarder-0.1.dist-info/RECORD
