Metadata-Version: 2.1
Name: typeguarder
Version: 0.1
Summary: Useful module for runtime type checking
Home-page: https://github.com/m00ga/typecheck
Author: m00ga
Author-email: UNKNOWN
License: UNKNOWN
Platform: UNKNOWN
